README.md
setup.py
bin/rimradio
rimradio/__init__.py
rimradio/rimradio.py
rimradio.egg-info/PKG-INFO
rimradio.egg-info/SOURCES.txt
rimradio.egg-info/dependency_links.txt
rimradio.egg-info/not-zip-safe
rimradio.egg-info/requires.txt
rimradio.egg-info/top_level.txt
rimradio/icons/__init__.py
rimradio/icons/play.png
rimradio/icons/stop.png