Metadata-Version: 1.1
Name: rimradio
Version: 0.1.2
Summary: Simple GTK stream radio player
Home-page: https://github.com/rimek/radio-gtk
Author: Marcin Rim
Author-email: rimek@poczta.fm
License: UNKNOWN
Platform: UNKNOWN
Classifier: Development Status :: 2 - Pre-Alpha
Classifier: Intended Audience :: Developers
Classifier: License :: OSI Approved :: BSD License
Classifier: Operating System :: OS Independent
Classifier: Programming Language :: Python
Classifier: Programming Language :: Python :: 3
